pkstl/__init__.py
pkstl/__test__.py
pkstl/libpkstl.so
pkstl-0.1.0.dist-info/LICENSE
pkstl-0.1.0.dist-info/METADATA
pkstl-0.1.0.dist-info/WHEEL
pkstl-0.1.0.dist-info/top_level.txt
pkstl-0.1.0.dist-info/RECORD
