Metadata-Version: 2.1
Name: pkstl
Version: 0.1.0
Summary: Public key secure transport layer
Home-page: https://git.duniter.org/tools/py-pkstl
Author: Pascal Engélibert
Author-email: tuxmain@zettascript.org
License: UNKNOWN
Keywords: security network transport cryptography
Platform: UNKNOWN
Classifier: Programming Language :: Python :: 3
Classifier: License :: OSI Approved :: GNU Affero General Public License v3
Classifier: Operating System :: OS Independent
Classifier: Topic :: Security :: Cryptography
Requires-Python: >=3.6
